valveexe/__init__.py
valveexe/console.py
valveexe/exe.py
valveexe/logger.py
valveexe/utils.py
valveexe-0.1.3.dist-info/LICENSE
valveexe-0.1.3.dist-info/METADATA
valveexe-0.1.3.dist-info/WHEEL
valveexe-0.1.3.dist-info/top_level.txt
valveexe-0.1.3.dist-info/RECORD
