Metadata-Version: 2.1
Name: valveexe
Version: 0.1.3
Summary: A library to issue console commands to Source Engine game clients
Home-page: https://pysourcesdk.github.io/ValveEXE/
Author: Maxime Dupuis
Author-email: mdupuis@hotmail.ca
License: gpl-3.0
Project-URL: Documentation, https://pysourcesdk.github.io/ValveEXE/
Project-URL: Github, https://github.com/pySourceSDK/ValveEXE
Keywords: exe,source,sourcesdk,hammer,valve,game,client
Classifier: Development Status :: 3 - Alpha 
Classifier: Intended Audience :: Developers
Classifier: Topic :: Software Development :: Build Tools
Classifier: License :: OSI Approved :: GNU General Public License v3 (GPLv3)
Classifier: Programming Language :: Python :: 3.7
Classifier: Programming Language :: Python :: 3.8
Classifier: Programming Language :: Python :: 3.9
Classifier: Programming Language :: Python :: 3.10
Classifier: Operating System :: Unix
Classifier: Operating System :: MacOS :: MacOS X
Classifier: Operating System :: Microsoft :: Windows
License-File: LICENSE
Requires-Dist: psutil
Requires-Dist: rcon
